relaner/__init__.py
relaner-0.0.1.dist-info/LICENSE
relaner-0.0.1.dist-info/METADATA
relaner-0.0.1.dist-info/WHEEL
relaner-0.0.1.dist-info/top_level.txt
relaner-0.0.1.dist-info/RECORD
