Metadata-Version: 2.2
Name: relaner
Version: 0.0.1
Summary: A RELation And Named Entity Recognition (RELANER) package
Home-page: https://github.com/alexmilowski/relaner
Author: Alex Miłowski
Author-email: alex@milowski.com
License: Apache License, Version 2.0, January 2004
Keywords: graph,relation extraction,named entity regonition
License-File: LICENSE
